[
  {
    "title": "Iran claims attacks on strait of Hormuz ships amid fresh US strikes – Middle East crisis live",
    "url": "https://www.theguardian.com/world/live/2026/jul/21/us-iran-war-live-updates-strait-of-hormuz-attacks-houthis-blockade-red-sea-middle-east-crisis-latest-news",
    "source": "The Guardian",
    "publishedAt": "2026-07-21T08:00:27Z"
  },
  {
    "title": "Why Trump is threatening new 50% tariffs on Canadian exports right now",
    "url": "https://www.cbc.ca/news/world/trump-tariffs-canada-why-now-9.7277446?cmp=rss",
    "source": "CBC",
    "publishedAt": "2026-07-21T08:00:00Z"
  },
  {
    "title": "Trump slaps 50% tariffs on Canada and Carney vows to 'intensify' trade talks",
    "url": "https://www.bbc.co.uk/news/articles/cg4dzq3x3e1o?at_medium=RSS&at_campaign=rss",
    "source": "BBC",
    "publishedAt": "2026-07-21T07:56:13Z"
  },
  {
    "title": "‘Active in BDS’: Document reveals how Israel scrutinised global NGOs",
    "url": "https://www.aljazeera.com/news/2026/7/21/critic-to-israel-document-reveals-how-israel-scrutinised-global-ngos?traffic_source=rss",
    "source": "Al Jazeera",
    "publishedAt": "2026-07-21T06:26:35Z"
  },
  {
    "title": "Almost 100 troops injured in recent weeks, Pentagon admits, as Iran launches reprisals on US allies",
    "url": "https://www.theguardian.com/world/2026/jul/21/us-troops-injured-killed-iran-war-attacks-pentagon",
    "source": "The Guardian",
    "publishedAt": "2026-07-21T04:09:54Z"
  },
  {
    "title": "China and Philippines trade accusations after sailor injured at sea",
    "url": "https://www.aljazeera.com/news/2026/7/21/china-and-philippines-trade-accusations-after-sailor-injured-at-sea?traffic_source=rss",
    "source": "Al Jazeera",
    "publishedAt": "2026-07-21T03:49:57Z"
  },
  {
    "title": "Donald Trump to impose 50% tariff on most Canadian goods, White House says",
    "url": "https://www.theguardian.com/us-news/2026/jul/20/trump-canada-tariffs",
    "source": "The Guardian",
    "publishedAt": "2026-07-21T02:29:47Z"
  },
  {
    "title": "Trump exploring additional tariffs on Canada for wildfire smoke impacts in US, White House official says –as it happened",
    "url": "https://www.theguardian.com/us-news/live/2026/jul/20/maine-democrats-troy-jackson-senate-graham-platner-donald-trump-immigration-world-cup-us-politics-latest-news-updates",
    "source": "The Guardian",
    "publishedAt": "2026-07-21T02:01:31Z"
  },
  {
    "title": "Trump imposes 50% US tariffs on some Canadian goods, citing discrimination",
    "url": "https://www.aljazeera.com/news/2026/7/21/trump-imposes-50-us-tariffs-on-some-canadian-goods-citing-discrimination?traffic_source=rss",
    "source": "Al Jazeera",
    "publishedAt": "2026-07-21T00:08:50Z"
  },
  {
    "title": "Despite the war, the U.S. and Iran are working together to deport asylum seekers, lawsuit says",
    "url": "https://www.cbc.ca/radio/asithappens/iran-us-asylum-lawsuit-9.7277110?cmp=rss",
    "source": "CBC",
    "publishedAt": "2026-07-20T23:11:47Z"
  },
  {
    "title": "‘Front groups and fellow travelers’: state department attacks US left over Cuba",
    "url": "https://www.theguardian.com/world/2026/jul/20/us-state-department-list-leftists-cuba",
    "source": "The Guardian",
    "publishedAt": "2026-07-20T22:50:46Z"
  },
  {
    "title": "Trump to hit Canada with new 50% tariff",
    "url": "https://www.cbc.ca/news/world/trump-canada-us-trade-tariffs-cusma-usmca-9.7276973?cmp=rss",
    "source": "CBC",
    "publishedAt": "2026-07-20T21:01:03Z"
  },
  {
    "title": "The war in Iran has left hundreds of U.S. diplomats in limbo",
    "url": "https://www.npr.org/2026/07/20/nx-s1-5896220/the-war-in-iran-has-left-hundreds-of-u-s-diplomats-in-limbo",
    "source": "NPR",
    "publishedAt": "2026-07-20T20:55:53Z"
  },
  {
    "title": "Does this video show Iranian missiles hitting a U.S. base?",
    "url": "https://www.cbc.ca/player/play/9.7277062?cmp=rss",
    "source": "CBC",
    "publishedAt": "2026-07-20T20:48:14Z"
  },
  {
    "title": "The war with Iran is escalating. What next?",
    "url": "https://www.npr.org/2026/07/20/nx-s1-5900950/the-war-with-iran-is-escalating-what-next",
    "source": "NPR",
    "publishedAt": "2026-07-20T19:56:49Z"
  },
  {
    "title": "Defence stocks rally as John Healey appointed chancellor; UK borrows less than expected in June – business live",
    "url": "https://www.theguardian.com/global/live/2026/jul/21/burnham-cuts-vat-electricity-bills-uk-borrowing-debt-economy-news-latest",
    "source": "The Guardian",
    "publishedAt": "2026-07-21T07:55:38Z"
  },
  {
    "title": "JP Morgan boss warns of ‘consequences’ if Burnham taxes banks",
    "url": "https://www.theguardian.com/business/2026/jul/21/jp-morgan-andy-burnham-tax-banks-jamie-dimon",
    "source": "The Guardian",
    "publishedAt": "2026-07-21T07:42:58Z"
  },
  {
    "title": "‘A partnership between settlers and the army’: two shot dead in latest West Bank raid",
    "url": "https://www.theguardian.com/world/2026/jul/20/israeli-settlers-partnership-army-palestinians-bury-dead-west-bank",
    "source": "The Guardian",
    "publishedAt": "2026-07-21T07:12:49Z"
  },
  {
    "title": "US launches fresh strikes on Iran, as Trump warns of retaliation for deaths of soldiers",
    "url": "https://www.bbc.co.uk/news/articles/cx25wg2x26do?at_medium=RSS&at_campaign=rss",
    "source": "BBC",
    "publishedAt": "2026-07-21T06:16:06Z"
  },
  {
    "title": "Canada issues air quality warnings over US wildfire smoke after Trump tariff threat",
    "url": "https://www.theguardian.com/world/2026/jul/20/canada-air-quality-warnings-us-wildfire-smoke-trump-tariffs",
    "source": "The Guardian",
    "publishedAt": "2026-07-20T15:52:58Z"
  }
]